MalCat-0.0.6.dist-info/DESCRIPTION.rst
MalCat-0.0.6.dist-info/METADATA
MalCat-0.0.6.dist-info/RECORD
MalCat-0.0.6.dist-info/WHEEL
MalCat-0.0.6.dist-info/metadata.json
MalCat-0.0.6.dist-info/top_level.txt
malcat/__init__.py
malcat/generator.py
malcat/series.py
malcat/status.py
myanimelist/__init__.py
myanimelist/api.py
myanimelist/models.py
