Metadata-Version: 2.0
Name: MalCat
Version: 0.0.6
Summary: MAL list-to-text processing utility.
Home-page: https://github.com/Doomcat55/MalCat
Author: Doomcat55
Author-email: Doomcat55@gmail.com
License: MIT
Platform: UNKNOWN
Classifier: Programming Language :: Python :: 2.7
Classifier: Programming Language :: Python :: 3.4
Requires-Dist: cssselect
Requires-Dist: lxml
Requires-Dist: requests
Requires-Dist: six
Requires-Dist: enum34; python_version < "3.4"
